gdbrunner/__init__.py
gdbrunner/backends.json
gdbrunner/cli.py
gdbrunner-0.0.5.dist-info/licenses/LICENSE
gdbrunner-0.0.5.dist-info/METADATA
gdbrunner-0.0.5.dist-info/WHEEL
gdbrunner-0.0.5.dist-info/entry_points.txt
gdbrunner-0.0.5.dist-info/top_level.txt
gdbrunner-0.0.5.dist-info/RECORD
