Metadata-Version: 2.4
Name: gdbrunner
Version: 0.0.5
Summary: GDB debug server launcher for embedded targets
Author-email: "OpenMV, LLC" <info@openmv.io>
License: MIT
Project-URL: Homepage, https://openmv.io
Project-URL: Repository, https://github.com/openmv/gdbrunner
Keywords: gdb,debug,embedded,jlink,stlink
Classifier: Development Status :: 4 - Beta
Classifier: Environment :: Console
Classifier: Intended Audience :: Developers
Classifier: License :: OSI Approved :: MIT License
Classifier: Operating System :: OS Independent
Classifier: Programming Language :: Python :: 3
Classifier: Topic :: Software Development :: Debuggers
Classifier: Topic :: Software Development :: Embedded Systems
Requires-Python: >=3.8
License-File: LICENSE
Dynamic: license-file
